matrixswarm/SAMPLE.agent.py
matrixswarm/SAMPLE.env
matrixswarm/__init__.py
matrixswarm/codex_gui.py
matrixswarm/command_handler.py
matrixswarm/encrypt_directive.py
matrixswarm/live_hive_watch.py
matrixswarm/main.py
matrixswarm/matrix_agent.py
matrixswarm/matrix_gui.py
matrixswarm/matrix_gui2.py
matrixswarm/site_boot.py
matrixswarm/site_kill.py
matrixswarm/site_list.py
matrixswarm/socket_communication.py
matrixswarm/swarm_bootstrap.py
matrixswarm/wss_client_test.py
matrixswarm/agent/__init__.py
matrixswarm/agent/agent_doctor/__init__.py
matrixswarm/agent/agent_doctor/agent_doctor.py
matrixswarm/agent/agent_health_probe/__init__.py
matrixswarm/agent/agent_health_probe/agent_health_probe.py
matrixswarm/agent/alarm_streamer/__init__.py
matrixswarm/agent/alarm_streamer/alarm_streamer.py
matrixswarm/agent/apache_watchdog/__init__.py
matrixswarm/agent/apache_watchdog/apache_watchdog.py
matrixswarm/agent/app_context/__init__.py
matrixswarm/agent/app_context/app_context.py
matrixswarm/agent/blank/__init__.py
matrixswarm/agent/blank/blank.py
matrixswarm/agent/capital_gpt/__init__.py
matrixswarm/agent/capital_gpt/capital_gpt.py
matrixswarm/agent/codex_verifier/__init__.py
matrixswarm/agent/codex_verifier/codex_verifier.py
matrixswarm/agent/commander/__init__.py
matrixswarm/agent/commander/commander.py
matrixswarm/agent/contact_reflex/__init__.py
matrixswarm/agent/contact_reflex/contact_reflex.py
matrixswarm/agent/crypto_alert/__init__.py
matrixswarm/agent/crypto_alert/crypto_alert.py
matrixswarm/agent/crypto_alert/factory/__init__.py
matrixswarm/agent/crypto_alert/factory/alarm/__init__.py
matrixswarm/agent/crypto_alert/factory/alert/__init__.py
matrixswarm/agent/crypto_alert/factory/codex/__init__.py
matrixswarm/agent/crypto_alert/factory/cryptocurrency/__init__.py
matrixswarm/agent/crypto_alert/factory/cryptocurrency/exchange/__init__.py
matrixswarm/agent/crypto_alert/factory/cryptocurrency/exchange/binance/__init__.py
matrixswarm-1.0.19.dist-info/licenses/LICENSE
matrixswarm-1.0.19.dist-info/METADATA
matrixswarm-1.0.19.dist-info/WHEEL
matrixswarm-1.0.19.dist-info/entry_points.txt
matrixswarm-1.0.19.dist-info/top_level.txt
matrixswarm-1.0.19.dist-info/RECORD
