Metadata-Version: 2.4
Name: matrixswarm
Version: 1.0.19
Summary: Open-source automation and monitoring platform
Author: MatrixSwarm Core Team (Daniel F. MacDonald, ChatGPT) AKA The Generals, Gemini Docstring Engineer
Author-email: swarm@matrixswarm.com
Requires-Python: >=3.8
License-File: LICENSE
Requires-Dist: aiohappyeyeballs==2.6.1
Requires-Dist: aiohttp==3.12.13
Requires-Dist: aiosignal==1.3.2
Requires-Dist: attrs==25.3.0
Requires-Dist: blinker==1.9.0
Requires-Dist: certifi==2025.6.15
Requires-Dist: cffi==1.17.1
Requires-Dist: charset-normalizer==3.4.2
Requires-Dist: click<8.2.0,>=8.0.0
Requires-Dist: cryptography==45.0.4
Requires-Dist: dotenv==0.9.9
Requires-Dist: Flask==3.1.1
Requires-Dist: frozenlist==1.7.0
Requires-Dist: geoip2==5.1.0
Requires-Dist: gevent==25.5.1
Requires-Dist: greenlet==3.2.3
Requires-Dist: idna==3.10
Requires-Dist: inotify==0.2.10
Requires-Dist: itsdangerous==2.2.0
Requires-Dist: Jinja2==3.1.6
Requires-Dist: MarkupSafe==3.0.2
Requires-Dist: maxminddb==2.7.0
Requires-Dist: multidict==6.5.1
Requires-Dist: nose==1.3.7
Requires-Dist: propcache==0.3.2
Requires-Dist: psutil==7.0.0
Requires-Dist: py-cord==2.6.1
Requires-Dist: pycparser==2.22
Requires-Dist: pycryptodome==3.23.0
Requires-Dist: python-dotenv==1.1.1
Requires-Dist: requests==2.32.4
Requires-Dist: setuptools==80.9.0
Requires-Dist: urllib3==2.5.0
Requires-Dist: websocket==0.2.1
Requires-Dist: websockets==15.0.1
Requires-Dist: Werkzeug==3.1.3
Requires-Dist: yarl==1.20.1
Requires-Dist: zope.event==5.1
Requires-Dist: zope.interface==7.2
Requires-Dist: eventlet
Requires-Dist: watchdog
Requires-Dist: openai
Requires-Dist: bleach
Dynamic: author
Dynamic: author-email
Dynamic: description
Dynamic: description-content-type
Dynamic: license-file
Dynamic: requires-dist
Dynamic: requires-python
Dynamic: summary
